GlamMonitor/Monitor.py
GlamMonitor/__init__.py
glammonitor-4.0.0.dist-info/METADATA
glammonitor-4.0.0.dist-info/WHEEL
glammonitor-4.0.0.dist-info/licenses/LICENSE
glammonitor-4.0.0.dist-info/RECORD
