Metadata-Version: 2.3
Name: GlamMonitor
Version: 4.0.0
Summary: Package to add logs that are stored in local and communicates start and end of processes with monitor API
Project-URL: Homepage, https://github.com/pypa/sampleproject
Project-URL: Bug Tracker, https://github.com/pypa/sampleproject/issues
Author-email: Glam Softwre 2012 SL <development@glamsw.com>
License-File: LICENSE
Classifier: License :: OSI Approved :: MIT License
Classifier: Operating System :: OS Independent
Classifier: Programming Language :: Python :: 3
Requires-Python: >=3.7
